README.md
setup.py
labelit/__init__.py
labelit/label.py
labelit/version.py
labelit.egg-info/PKG-INFO
labelit.egg-info/SOURCES.txt
labelit.egg-info/dependency_links.txt
labelit.egg-info/not-zip-safe
labelit.egg-info/requires.txt
labelit.egg-info/top_level.txt
labelit/active_learning/__init__.py
labelit/active_learning/choose_samples.py
labelit/active_learning/tf_create_data.py
labelit/active_learning/tf_run_experiment.py
labelit/active_learning/sampler/__init__.py
labelit/active_learning/sampler/bandit_discrete.py
labelit/active_learning/sampler/constants.py
labelit/active_learning/sampler/graph_density.py
labelit/active_learning/sampler/hierarchical_clustering_AL.py
labelit/active_learning/sampler/informative_diverse.py
labelit/active_learning/sampler/kcenter_greedy.py
labelit/active_learning/sampler/margin_AL.py
labelit/active_learning/sampler/mixture_of_samplers.py
labelit/active_learning/sampler/represent_cluster_centers.py
labelit/active_learning/sampler/sampling_def.py
labelit/active_learning/sampler/simulate_batch.py
labelit/active_learning/sampler/uniform_sampling.py
labelit/active_learning/sampler/wrapper_sampler_def.py
labelit/active_learning/scorer/__init__.py
labelit/active_learning/scorer/allconv.py
labelit/active_learning/scorer/kernel_block_solver.py
labelit/active_learning/scorer/score_methods.py
labelit/active_learning/scorer/small_cnn.py
labelit/data/sentence_symbol.txt
labelit/data/stop_words.txt
labelit/models/__init__.py
labelit/models/classic_model.py
labelit/models/evaluate.py
labelit/models/feature.py
labelit/utils/__init__.py
labelit/utils/data_utils.py
labelit/utils/io_utils.py