Metadata-Version: 2.1
Name: labelit
Version: 0.1.5
Summary: label text and image based on active learning.
Home-page: https://github.com/shibing624/labelit
Author: XuMing
Author-email: xuming624@qq.com
License: Apache 2.0
Keywords: labelit,active learning,label text,label image
Platform: Windows
Platform: Linux
Platform: Solaris
Platform: Mac OS-X
Platform: Unix
Classifier: Intended Audience :: Developers
Classifier: Operating System :: OS Independent
Classifier: Natural Language :: Chinese (Simplified)
Classifier: Natural Language :: Chinese (Traditional)
Classifier: Programming Language :: Python
Classifier: Programming Language :: Python :: 3
Classifier: Topic :: Text Processing :: Linguistic
Classifier: Topic :: Scientific/Engineering :: Artificial Intelligence
Requires-Python: >=3.5
